pipesnake/__init__.py
pipesnake/metadata.py
pipesnake/base/__init__.py
pipesnake/base/abstract.py
pipesnake/base/utils.py
pipesnake/pipe/__init__.py
pipesnake/pipe/parallel.py
pipesnake/pipe/series.py
pipesnake/transformers/__init__.py
pipesnake/transformers/combiner.py
pipesnake/transformers/converter.py
pipesnake/transformers/deeplearning.py
pipesnake/transformers/dropper.py
pipesnake/transformers/financial.py
pipesnake/transformers/imputer.py
pipesnake/transformers/misc.py
pipesnake/transformers/scaler.py
pipesnake/transformers/selector.py
pipesnake/transformers/stats.py
pipesnake/utils/__init__.py
pipesnake/utils/decorator.py
pipesnake/utils/graph.py
pipesnake/utils/persistance.py
pipesnake-0.1.dist-info/DESCRIPTION.rst
pipesnake-0.1.dist-info/METADATA
pipesnake-0.1.dist-info/RECORD
pipesnake-0.1.dist-info/WHEEL
pipesnake-0.1.dist-info/metadata.json
pipesnake-0.1.dist-info/top_level.txt
